CHANGES.rst
LICENSE.txt
MANIFEST.in
README.rst
setup.py
django_mediastore.egg-info/PKG-INFO
django_mediastore.egg-info/SOURCES.txt
django_mediastore.egg-info/dependency_links.txt
django_mediastore.egg-info/not-zip-safe
django_mediastore.egg-info/requires.txt
django_mediastore.egg-info/top_level.txt
mediastore/__init__.py
mediastore/admin.py
mediastore/conf.py
mediastore/forms.py
mediastore/models.py
mediastore/preview.py
mediastore/template.py
mediastore/widgets.py
mediastore/fields/__init__.py
mediastore/fields/file.py
mediastore/fields/related.py
mediastore/mediatypes/__init__.py
mediastore/mediatypes/audio/__init__.py
mediastore/mediatypes/audio/admin.py
mediastore/mediatypes/audio/models.py
mediastore/mediatypes/audio/templates/mediastore/types/audio/display.html
mediastore/mediatypes/audio/templates/mediastore/types/audio/preview.html
mediastore/mediatypes/download/__init__.py
mediastore/mediatypes/download/admin.py
mediastore/mediatypes/download/models.py
mediastore/mediatypes/download/views.py
mediastore/mediatypes/download/templates/mediastore/types/download/display.html
mediastore/mediatypes/download/templates/mediastore/types/download/display_many.html
mediastore/mediatypes/download/templates/mediastore/types/download/preview.html
mediastore/mediatypes/embeded/__init__.py
mediastore/mediatypes/embeded/admin.py
mediastore/mediatypes/embeded/models.py
mediastore/mediatypes/embeded/templates/mediastore/types/embeded/display.html
mediastore/mediatypes/embeded/templates/mediastore/types/embeded/preview.html
mediastore/mediatypes/image/__init__.py
mediastore/mediatypes/image/admin.py
mediastore/mediatypes/image/batchupload.py
mediastore/mediatypes/image/models.py
mediastore/mediatypes/image/templates/admin/mediastore/image/add_many_form.html
mediastore/mediatypes/image/templates/admin/mediastore/image/change_list.html
mediastore/mediatypes/image/templates/mediastore/types/image/display.html
mediastore/mediatypes/image/templates/mediastore/types/image/preview.html
mediastore/mediatypes/pdf/__init__.py
mediastore/mediatypes/pdf/admin.py
mediastore/mediatypes/pdf/models.py
mediastore/mediatypes/pdf/templates/mediastore/types/pdf/display.html
